[
  {
    "id": "matador1",
    "title": "Matador BBQ Pit",
    "description": "This is a BBQ Restaurant",
    "summary": "A Down-to-Earth BBQ Joint serving up classic BBQ meals in a casual setting.",
    "address": "18111 Nordhoff St, Northridge",
    "rating": 5.0,
    "reviews": 1243,
    "genre": "Barbecue",
    "price": "$$$",
    "seating": "Indoor",
    "lat": 34.23796594969169,
    "lng": -118.53662856651358,
    "image": "lib/Assets/BBQ.jpg",
    "layout": [
      { "id": "table1", "x": 50, "y": 50, "width": 100, "height": 100, "available": true },
      { "id": "table2", "x": 250, "y": 50, "width": 100, "height": 100, "available": true },
      { "id": "table3", "x": 50, "y": 200, "width": 100, "height": 100, "available": true },
      { "id": "table4", "x": 250, "y": 200, "width": 100, "height": 100, "available": true },
      { "id": "table5", "x": 50, "y": 350, "width": 100, "height": 100, "available": true },
      { "id": "table6", "x": 250, "y": 350, "width": 100, "height": 100, "available": true }
    ],
    "menu": [
      {
        "name": "BBQ Chicken",
        "price": 12.99,
        "description": "Grilled chicken with BBQ sauce."
      },
      {
        "name": "Pulled Pork Sandwich",
        "price": 10.99,
        "description": "Slow-cooked pulled pork on a bun."
      },
      {
        "name": "Ribs",
        "price": 15.99,
        "description": "Tender ribs with house-made BBQ sauce."
      },
      {
        "name": "Brisket Platter",
        "price": 18.99,
        "description": "Smoked brisket served with sides."
      },
      {
        "name": "Cornbread",
        "price": 3.99,
        "description": "Sweet cornbread served with butter."
      },
      {
        "name": "Coleslaw",
        "price": 2.99,
        "description": "Creamy coleslaw with shredded cabbage and carrots."
      },
      {
        "name": "BBQ Beans",
        "price": 3.99,
        "description": "Baked beans with BBQ sauce."
      },
      {
        "name": "Mac and Cheese",
        "price": 4.99,
        "description": "Creamy macaroni and cheese."
      }
    ]
  },
  {
    "id": "matador5",
    "title": "Pekingham Palace",
    "description": "A british/chinese fusion restaurant",
    "summary": "A fusion restaurant",
    "address": "18103 Nordhoff St, Northridge",
    "rating": 0.0,
    "reviews": 4326,
    "genre": "British/Chinese",
    "price": "$$",
    "seating": "Indoor",
    "lat": 34.243181956884065,
    "lng": -118.52853961742417,
    "image": "lib/Assets/pekinghampalace_logo.png",
    "layout": [
      { "id": "table1", "x": 75, "y": 50, "width": 250, "height": 75, "available": true },
      { "id": "table2", "x": 75, "y": 200, "width": 250, "height": 75, "available": true },
      { "id": "table3", "x": 50, "y": 350, "width": 100, "height": 100, "available": true },
      { "id": "table4", "x": 250, "y": 350, "width": 100, "height": 100, "available": true },
      { "id": "table5", "x": 50, "y": 500, "width": 100, "height": 100, "available": true },
      { "id": "table6", "x": 250, "y": 500, "width": 100, "height": 100, "available": true }
    ],
    "menu": [
      {
        "name": "Full English Bibimbap",
        "price": 14.99,
        "description": "A full english breakfast, slapped over hot rice with the national british museum's culture-swiping confusion."
      },

      {
        "name": "Century Scotch Egg",
        "price": 4.99,
        "description": "A century egg wrapped in sausage and deep fried."
      },
      {
        "name": "The Big Beige™",
        "price": 29.99,
        "description": "A plate of the finest chinese takeaway, perfectly color matched to the color of your nan's wallpaper."
      },
      {
        "name": "Mushy Pea Wonton Soup",
        "price": 7.99,
        "description": "A bowl of wonton soup with wontons filled with mushy peas."
      },
      {
        "name": "Lukewarm Pot",
        "price": 8.99,
        "description": "Lukewarm soup accompanied with fried meats and NO vegetables to dip into"
      },
      {
        "name": "Mushy Pea Wonton Soup",
        "price": 7.99,
        "description": "A bowl of wonton soup with wontons filled with mushy peas."
      },
      {
        "name": "The Boba Milk Pea",
        "price": 5.99,
        "description": "A Special Milk tea with peas instead of boba."
      },
      {
        "name": "Chicken Tikka Mochisala",
        "price": 12.99,
        "description": "Mochi filled with chicken tikka masala. Cold."
      },
      {
        "name": "Jellied Eel Rangoon",
        "price": 6.99,
        "description": "A fried wonton filled with jellied eel. Eat at your own risk."
      },
      {
        "name": "Fortune Biscuits",
        "price": 2.99,
        "description": "A buscuit with a fortune inside. The fortune is always 'You will die alone'."
      }
    ]
  },
  {
    "id": "matador6",
    "title": "Giordanacho's",
    "description": "Italian nacho fusion, they just throw spaghetti on top of nachos",
    "summary": "Classic Italian Kitchen serving up Italian Mexican dishes. The head chef does NOT know how to cook.",
    "address": "18401 Nordhoff St, Northridge",
    "rating": 2.5,
    "reviews": 15,
    "genre": "Italian Mexican",
    "price": "$$",
    "seating": "Indoor (Food Court)",
    "lat": 34.2357274106314,
    "lng": -118.53403046268451,
    "image": "lib/Assets/giordanachos.png",
    "layout": [
      { "id": "table1", "x": 40, "y": 100, "width": 120, "height": 75, "available": true },
      { "id": "table2", "x": 240, "y": 100, "width": 120, "height": 75, "available": true },
      { "id": "table3", "x": 40, "y": 250, "width": 120, "height": 75, "available": true },
      { "id": "table4", "x": 240, "y": 250, "width": 120, "height": 75, "available": true },
      { "id": "table5", "x": 50, "y": 400, "width": 100, "height": 100, "available": true },
      { "id": "table6", "x": 250, "y": 400, "width": 100, "height": 100, "available": true }
    ],
    "menu": [
      {
        "name": "Nacho Mama's Spaghetti",
        "price": 13.99,
        "description": "Spaghetti topped with nacho cheese and jalapenos."
      },
      {
        "name": "Classic Spaghachos",
        "price": 15.99,
        "description": "Nachos topped with spaghetti, marinara sauce, and mozzarella cheese."
      },
      {
        "name": "Alfre-Don Julio Crunchip XXL",
        "price": 49.99,
        "description": "An oversized plate of nachos topped with Alfredo sauce, ground beef, and jalapenos."
      },
      {
        "name": "Torta-llini",
        "price": 5.99,
        "description": "Nachos topped with tortellini and marinara sauce."
      },
      {
        "name": "Pastaquitos",
        "price": 7.99,
        "description": "Nachos topped with pasta and cheese."
      },
      {
        "name": "Spaghetti Fries",
        "price": 4.99,
        "description": "Fries topped with spaghetti and marinara sauce."
      },
      {
        "name": "Nacho Pizza",
        "price": 12.99,
        "description": "Pizza topped with nachos and cheese."
      },
      {
        "name": "Spaghetti Salad",
        "price": 6.99,
        "description": "Salad topped with spaghetti and dressing."
      }
    ]
  },
  {
    "id": "matador2",
    "title": "The 818 Eatery",
    "description": "A small cafe/restaraunt",
    "summary": "A cozy cafe with a few food options and a great place to relax.",
    "address": "18123 Nordhoff St, Northridge",
    "rating": 4.5,
    "reviews": 2,
    "genre": "Cafe/Breakfast",
    "price": "$$",
    "seating": "Indoor/Outdoor",
    "lat": 34.23982826085725,
    "lng": -118.52539003612064,
    "image": "lib/Assets/KC310124-27.jpg",
    "layout": [
      { "id": "table1", "x": 30, "y": 80, "width": 75, "height": 200, "available": true },
      { "id": "table2", "x": 165, "y": 80, "width": 75, "height": 200, "available": true },
      { "id": "table3", "x": 300, "y": 80, "width": 75, "height": 200, "available": true },
      { "id": "table4", "x": 50, "y": 330, "width": 100, "height": 100, "available": true },
      { "id": "table5", "x": 250, "y": 330, "width": 100, "height": 100, "available": true },
      { "id": "table6", "x": 150, "y": 480, "width": 100, "height": 100, "available": true }
    ],
    "menu": [
      {
        "name": "Breakfast Burrito",
        "price": 8.99,
        "description": "Eggs, cheese, and salsa in a tortilla."
      },
      {
        "name": "Avocado Toast",
        "price": 7.99,
        "description": "Smashed avocado on toasted bread."
      },
      {
        "name": "Iced Coffee",
        "price": 3.99,
        "description": "Chilled coffee with milk and sugar."
      },
      {
        "name": "Fruit Salad",
        "price": 5.99,
        "description": "Fresh seasonal fruit salad."
      },
      {
        "name": "Caesar Salad",
        "price": 6.99,
        "description": "Romaine lettuce, croutons, and Caesar dressing."
      },
      {
        "name": "Pancakes",
        "price": 6.99,
        "description": "Fluffy pancakes served with syrup."
      },
      {
        "name": "French Toast",
        "price": 7.99,
        "description": "Thick slices of bread dipped in egg and grilled."
      },
      {
        "name": "Omelette",
        "price": 9.99,
        "description": "Egg omelette with cheese and veggies."
      }
    ]
  },
  {
    "id": "matador3",
    "title": "Northridge Bites",
    "description": "Cafe with a few food options",
    "summary": "A small cafe with a few food options and a great place to relax.",
    "address": "18127 Zelzah Ave, Northridge",
    "rating": 4.0,
    "reviews": 498,
    "genre": "Cafe",
    "price": "$",
    "seating": "Indoor/Outdoor",
    "lat": 34.24131729261727,
    "lng": -118.5296862650247,
    "image": "lib/Assets/Bites.jpg",
    "layout": [
      { "id": "table1", "x": 50, "y": 100, "width": 100, "height": 100, "available": true },
      { "id": "table2", "x": 250, "y": 100, "width": 100, "height": 100, "available": true },
      { "id": "table3", "x": 50, "y": 250, "width": 100, "height": 100, "available": true },
      { "id": "table4", "x": 250, "y": 250, "width": 100, "height": 100, "available": true },
      { "id": "table5", "x": 50, "y": 400, "width": 100, "height": 100, "available": true },
      { "id": "table6", "x": 250, "y": 400, "width": 100, "height": 100, "available": true }
    ],
    "menu": [
      {
        "name": "Veggie Wrap",
        "price": 6.99,
        "description": "Fresh veggies wrapped in a tortilla."
      },
      {
        "name": "Fruit Smoothie",
        "price": 4.99,
        "description": "Blended fruit smoothie with yogurt."
      },
      {
        "name": "Chili Cheese Fries",
        "price": 5.99,
        "description": "Fries topped with chili and cheese."
      },
      {
        "name": "Breakfast Sandwich",
        "price": 7.99,
        "description": "Egg, cheese, and bacon on a bagel."
      },
      {
        "name": "Iced Latte",
        "price": 4.49,
        "description": "Chilled espresso with milk and ice."
      },
      {
        "name": "Bagel with Cream Cheese",
        "price": 2.99,
        "description": "Toasted bagel with cream cheese."
      },
      {
        "name": "Croissant",
        "price": 3.49,
        "description": "Flaky croissant pastry."
      },
      {
        "name": "Muffin",
        "price": 2.49,
        "description": "Freshly baked muffin."
      }
    ]
  },
  {
    "id": "matador4",
    "title": "Freddy Fazbear's Pizza",
    "description": "Har har har har har har har har",
    "summary": "A family-friendly pizzeria with animatronic mascots, arcade games, and a fun atmosphere!",
    "address": "18000 Nordhoff St, Northridge",
    "rating": 1.0,
    "reviews": 5213,
    "genre": "Pizzeria",
    "price": "$",
    "seating": "Indoor",
    "lat": 34.2381180947572,
    "lng": -118.53078391029187,
    "image": "lib/Assets/Pizza.jpg",
    "layout": [
      { "id": "table1", "x": 30, "y": 50, "width": 75, "height": 275, "available": true },
      { "id": "table2", "x": 165, "y": 50, "width": 75, "height": 275, "available": true },
      { "id": "table3", "x": 300, "y": 50, "width": 75, "height": 275, "available": true },
      { "id": "table4", "x": 30, "y": 375, "width": 75, "height": 275, "available": true },
      { "id": "table5", "x": 165, "y": 375, "width": 75, "height": 275, "available": true },
      { "id": "table6", "x": 300, "y": 375, "width": 75, "height": 275, "available": true }
    ],
    "menu": [
      {
        "name": "Cheese Pizza",
        "price": 9.99,
        "description": "Classic cheese pizza with marinara sauce."
      },
      {
        "name": "Pepperoni Pizza",
        "price": 10.99,
        "description": "Pepperoni pizza with mozzarella cheese."
      },
      {
        "name": "Veggie Pizza",
        "price": 11.99,
        "description": "Pizza topped with fresh vegetables."

      },
      {
        "name": "Garlic Knots",
        "price": 5.99,
        "description": "Garlic knots served with marinara sauce."
      },
      {
        "name": "Caesar Salad",
        "price": 6.99,
        "description": "Romaine lettuce, croutons, and Caesar dressing."
      },
      {
        "name": "Buffalo Wings",
        "price": 8.99,
        "description": "Spicy buffalo wings served with ranch dressing."
      },
      {
        "name": "Desert Pizza",
        "price": 12.99,
        "description": "Pizza topped with chocolate and marshmallows."
      },
      {
        "name": "Soda",
        "price": 1.99,
        "description": "Soft drink of your choice."
      }
    ]
  }
]